{
  "primitives": {
    "space": {
      "xs": {
        "value": "4px",
        "type": "dimension"
      },
      "sm": {
        "value": "8px",
        "type": "dimension"
      },
      "md": {
        "value": "16px",
        "type": "dimension"
      }
    }
  },

  "semantics": {
    "space": {
      "tight": {
        "value": "{primitives.space.xs}",
        "type": "dimension"
      },
      "comfortable": {
        "value": "{primitives.space.md}",
        "type": "dimension"
      }
    }
  }
}
